osfa/__init__.py
osfa/__main__.py
osfa/osfa.py
osfa-1.1.dist-info/LICENSE
osfa-1.1.dist-info/METADATA
osfa-1.1.dist-info/WHEEL
osfa-1.1.dist-info/top_level.txt
osfa-1.1.dist-info/RECORD
