Metadata-Version: 2.1
Name: osfa
Version: 1.1
Summary: One Shell For All
Home-page: https://github.com/FreehandBlock51/OSFA
Author: FreehandBlock51
Author-email: freehandblock51@outlook.com
License: UNKNOWN
Project-URL: Bug Tracker, https://github.com/FreehandBlock51/OSFA/issues
Platform: UNKNOWN
Classifier: Programming Language :: Python :: 3
Classifier: License :: OSI Approved :: MIT License
Classifier: Operating System :: OS Independent
Requires-Python: >=3.6
License-File: LICENSE
